factorial_app_69420/__init__.py
factorial_app_69420/app.py
factorial_app_69420/factorial.py
factorial_app_69420-0.1.0.dist-info/METADATA
factorial_app_69420-0.1.0.dist-info/WHEEL
factorial_app_69420-0.1.0.dist-info/RECORD
